autora/experimentalist/divergence/__init__.py
autora_experimentalist_divergence-0.0.2.dist-info/LICENSE
autora_experimentalist_divergence-0.0.2.dist-info/METADATA
autora_experimentalist_divergence-0.0.2.dist-info/WHEEL
autora_experimentalist_divergence-0.0.2.dist-info/top_level.txt
autora_experimentalist_divergence-0.0.2.dist-info/RECORD
