Metadata-Version: 2.1
Name: autora_experimentalist_divergence
Version: 0.0.2
Summary: sampling based on divergence
Author-email: Younes Strittmatter <younes.strittmatter@brown.edu>
License: Copyright (c) 2024 Younes Strittmatter
Project-URL: homepage, http://www.empiricalresearch.ai
Project-URL: repository, https://github.com/AutoResearch/autora-experimentalist-divergence
Project-URL: documentation, https://autoresearch.github.io/autora/
Requires-Python: <4,>=3.8
License-File: LICENSE
Requires-Dist: autora-core
Requires-Dist: scikit-learn
Provides-Extra: dev
Requires-Dist: autora-core[dev] ; extra == 'dev'
